[{"name":"Southeast"},{"name":"Mountain"},{"name":"West"},{"name":"South Central"},{"name":"South"},{"name":"Great Lakes"},{"name":"Midwest"},{"name":"Northeast"},{"name":"Mid-Atlantic"},{"name":"DII Midwest"},{"name":"DII South Central"},{"name":"DII Southeast"},{"name":"DIII Mideast"},{"name":"DII South"},{"name":"DII Central"},{"name":"DIII New England"},{},{"name":"DIII Midwest"},{"name":"DII West"},{"name":"DIII Central"},{"name":"DIII Atlantic"},{"name":"DIII West"},{"name":"DII East"},{"name":"DIII Great Lakes"},{"name":"DIII South/Southeast"},{"name":"DII Atlantic"},{"name":"East"},{"name":"DIIMidwest"},{"name":"DII MIdwest"},{"name":"Central"},{"name":"Atlantic"},{"name":"Mideast"},{"name":"New England"},{"name":"South/Southeast"}]
